pxweb/__init__.py
pxweb/_version.py
pxweb/api.py
pxweb/py.typed
pxweb/_internal/__init__.py
pxweb/_internal/client.py
pxweb/_internal/functions.py
pxwebpy-0.5.5.dist-info/METADATA
pxwebpy-0.5.5.dist-info/WHEEL
pxwebpy-0.5.5.dist-info/licenses/LICENSE
pxwebpy-0.5.5.dist-info/RECORD
