Metadata-Version: 2.4
Name: pxwebpy
Version: 0.5.5
Summary: Client library for the PxWeb API to easily load data into a DataFrame.
Project-URL: Repository, https://github.com/stefur/pxwebpy
Project-URL: Documentation, https://stefur.github.io/pxwebpy
Author-email: Stefan Furne <stefan@furne.net>
License-Expression: MIT
License-File: LICENSE
Keywords: dataframes,pandas,polars,pxweb,statistics
Classifier: License :: OSI Approved :: MIT License
Classifier: Programming Language :: Python :: 3 :: Only
Classifier: Programming Language :: Python :: 3.10
Classifier: Programming Language :: Python :: 3.11
Classifier: Programming Language :: Python :: 3.12
Classifier: Programming Language :: Python :: 3.13
Classifier: Programming Language :: Python :: 3.14
Requires-Python: >=3.10
Requires-Dist: packaging>=25.0
Requires-Dist: requests-cache>=1.2.1
Requires-Dist: requests>=2.32.3
